practice/ex1.v
module and_self(input a, b, output reg c);
always @(*) begin
    c = a & b;
end
endmodule

module or_self(input a, b, output reg c);
always @(*) begin
    c = a | b;
    c = ~c; 
end
endmodule

module xor_self(input a, b, output reg c);
always @(*) begin
    c = a & ~b | ~a & b;
end
endmodule

module cir(input a, b, c, d, output wire o);
wire [1:0]q;
and_self a1(a, b, q[0]);
or_self a2(c, d, q[1]);
xor_self a3(q[0], q[1], o);
endmodule

module tb_cir;
reg a,b,c,d;
wire o;
integer i;
cir test(a,b,c,d,o);
initial begin
    a = 0;
    b = 0;
    c = 0;
    d = 0;
   // seting up the vcd dump file
   $dumpfile("ex1.vcd");
   $dumpvars(0, tb_cir) ;
    $monitor ("a = %b, b = %b, c = %b, d = %b, o = %b",a,b,c,d,o);
    for (i = 0; i < 16; i++)
    begin
    {a,b,c,d} = i;
    #10;
    end
    $finish;
    
end
endmodule

practice/ex1.vcd
$date
	Mon Mar 31 11:20:52 2025
$end
$version
	Icarus Verilog
$end
$timescale
	1s
$end
$scope module tb_cir $end
$var wire 1 ! o $end
$var reg 1 " a $end
$var reg 1 # b $end
$var reg 1 $ c $end
$var reg 1 % d $end
$var integer 32 & i [31:0] $end
$scope module test $end
$var wire 1 " a $end
$var wire 1 # b $end
$var wire 1 $ c $end
$var wire 1 % d $end
$var wire 2 ' q [1:0] $end
$var wire 1 ! o $end
$scope module a1 $end
$var wire 1 " a $end
$var wire 1 # b $end
$var reg 1 ( c $end
$upscope $end
$scope module a2 $end
$var wire 1 $ a $end
$var wire 1 % b $end
$var reg 1 ) c $end
$upscope $end
$scope module a3 $end
$var wire 1 * a $end
$var wire 1 + b $end
$var reg 1 ! c $end
$upscope $end
$upscope $end
$upscope $end
$enddefinitions $end
$comment Show the parameter values. $end
$dumpall
$end
#0
$dumpvars
1+
0*
1)
0(
b10 '
b0 &
0%
0$
0#
0"
1!
$end
#10
0!
0+
b0 '
0)
1%
b1 &
#20
b0 '
0)
1$
0%
b10 &
#30
b0 '
0)
1%
b11 &
#40
1!
1+
b10 '
1)
1#
0$
0%
b100 &
#50
0!
0+
b0 '
0)
1%
b101 &
#60
b0 '
0)
1$
0%
b110 &
#70
b0 '
0)
1%
b111 &
#80
1!
1+
b10 '
1)
1"
0#
0$
0%
b1000 &
#90
0!
0+
b0 '
0)
1%
b1001 &
#100
b0 '
0)
1$
0%
b1010 &
#110
b0 '
0)
1%
b1011 &
#120
1*
1+
1(
b11 '
1)
1#
0$
0%
b1100 &
#130
1!
0+
b1 '
0)
1%
b1101 &
#140
b1 '
0)
1$
0%
b1110 &
#150
b1 '
0)
1%
b1111 &
#160
b10000 &
