processorDesign/practice/parityFSM.v
// parity one => even
// parity zero => odd

module parityFSM (
    parity,
    data,
    clk
);
    input data, clk;
    output reg parity = 1;

    always @(posedge clk) begin
        if (parity == 1'b1) parity = data ? 0 : 1;
        else if (parity == 1'b0) parity = data ? 1 : 0;
    end
endmodule

module tb;
    parameter N = 8;
    reg [N-1:0] data;
    reg tempData = 0;
    reg clk;
    wire parity;
    parityFSM par (
        .parity(parity),
        .data(tempData),
        .clk(clk)
    );
    initial begin
        $dumpfile("parityFSM.vcd");
        $dumpvars(0, par);
        clk = 0;
        forever #5 clk = ~clk;
    end
    initial begin
        #150 $finish;
    end
    integer i;
    initial begin
        data = 8'd101;
        i = 0;
        #2;
        for (i = 0; i < N; i = i + 1) begin
            #10 tempData = data[i];
        end
        #10 $display("parity:%b, data:%b", parity, data);
    end
endmodule

processorDesign/practice/parityFSM.vcd
$date
	Sat Apr 12 09:30:29 2025
$end
$version
	Icarus Verilog
$end
$timescale
	1s
$end
$scope module tb $end
$scope module par $end
$var wire 1 ! clk $end
$var wire 1 " data $end
$var reg 1 # parity $end
$upscope $end
$upscope $end
$enddefinitions $end
$comment Show the parameter values. $end
$dumpall
$end
#0
$dumpvars
1#
0"
0!
$end
#5
1!
#10
0!
#12
1"
#15
0#
1!
#20
0!
#22
0"
#25
1!
#30
0!
#32
1"
#35
1#
1!
#40
0!
#42
0"
#45
1!
#50
0!
#55
1!
#60
0!
#62
1"
#65
0#
1!
#70
0!
#75
1#
1!
#80
0!
#82
0"
