processorDesign/practice/sequenceDetector.v
// detect a sequence 0110 in a input bit stream

module sequenceDetector (
    z,
    x,
    clk
);
    output reg z;
    input x, clk;
    reg [2:0] PS = 3'b000;
    parameter state0 = 3'b000;
    parameter state1 = 3'b001;
    parameter state2 = 3'b010;
    parameter state3 = 3'b011;

    always @(posedge clk) begin

        if (PS == state0) begin
            PS = (x == 0) ? state1 : state0;  // X
            z  = 0;
        end else if (PS == state1) begin
            PS = (x == 1) ? state2 : state1;  // 0X
            z  = 0;
        end else if (PS == state2) begin
            PS = (x == 1) ? state3 : state1;  //01X
            z  = 0;
        end else if (PS == state3) begin
            z  = (x == 0) ? 1 : 0;
            PS = (x == 0) ? state1 : state0;  // 011X
        end

    end

endmodule

module tb;
    reg clk;
    parameter N = 16;
    reg [N-1:0] x;
    wire z;
    reg data;
    sequenceDetector detect (
        .z  (z),
        .x  (data),
        .clk(clk)
    );
    initial begin
        clk = 0;
        forever #5 clk = ~clk;
    end
    integer i;
    initial begin
        $dumpfile("sequenceDetector.vcd");
        $dumpvars(0, tb);
        x = 16'b0000_0110_0000_0110;
        data = 0;
        #2;
        for (i = 0; i < N; i++) begin
            #10 data = x[i];
        end
        #10 $finish;
    end
    initial $monitor("z:%b, data:%b, clk:%b", z, data, clk);
endmodule

processorDesign/practice/sequenceDetector.vcd
$date
	Sat Apr 12 11:31:58 2025
$end
$version
	Icarus Verilog
$end
$timescale
	1s
$end
$scope module tb $end
$var wire 1 ! z $end
$var parameter 32 " N $end
$var reg 1 # clk $end
$var reg 1 $ data $end
$var reg 16 % x [15:0] $end
$var integer 32 & i [31:0] $end
$scope module detect $end
$var wire 1 # clk $end
$var wire 1 $ x $end
$var parameter 3 ' state0 $end
$var parameter 3 ( state1 $end
$var parameter 3 ) state2 $end
$var parameter 3 * state3 $end
$var reg 3 + PS [2:0] $end
$var reg 1 ! z $end
$upscope $end
$upscope $end
$enddefinitions $end
$comment Show the parameter values. $end
$dumpall
b11 *
b10 )
b1 (
b0 '
b10000 "
$end
#0
$dumpvars
b0 +
bx &
b11000000110 %
0$
0#
x!
$end
#2
b0 &
#5
0!
b1 +
1#
#10
0#
#12
b1 &
#15
1#
#20
0#
#22
b10 &
1$
#25
b10 +
1#
#30
0#
#32
b11 &
#35
b11 +
1#
#40
0#
#42
b100 &
0$
#45
b1 +
1!
1#
#50
0#
#52
b101 &
#55
0!
1#
#60
0#
#62
b110 &
#65
1#
#70
0#
#72
b111 &
#75
1#
#80
0#
#82
b1000 &
#85
1#
#90
0#
#92
b1001 &
#95
1#
#100
0#
#102
b1010 &
1$
#105
b10 +
1#
#110
0#
#112
b1011 &
#115
b11 +
1#
#120
0#
#122
b1100 &
0$
#125
b1 +
1!
1#
#130
0#
#132
b1101 &
#135
0!
1#
#140
0#
#142
b1110 &
#145
1#
#150
0#
#152
b1111 &
#155
1#
#160
0#
#162
b10000 &
